pydb/__init__.py
pydb/orm.py
pydb_sql-0.1.0.dist-info/licenses/LICENSE
pydb_sql-0.1.0.dist-info/METADATA
pydb_sql-0.1.0.dist-info/WHEEL
pydb_sql-0.1.0.dist-info/top_level.txt
pydb_sql-0.1.0.dist-info/RECORD
