Metadata-Version: 2.4
Name: pydb-sql
Version: 0.1.0
Summary: A lightweight Mongoose-inspired SQL ORM for Python
Author-email: Satyam Rana <your-email@example.com>
Project-URL: Homepage, https://github.com/satyamrana/PyOrm
Project-URL: Bug Tracker, https://github.com/satyamrana/PyOrm/issues
Classifier: Programming Language :: Python :: 3
Classifier: License :: OSI Approved :: MIT License
Classifier: Operating System :: OS Independent
Requires-Python: >=3.7
License-File: LICENSE
Requires-Dist: mysql-connector-python>=8.0.0
Dynamic: license-file
